.coveragerc
.gitignore
LICENSE
MANIFEST.in
README.md
citation.cff
manifest.xml
pyproject.toml
requirements.txt
setup.cfg
setup.py
.github/workflows/python-package.yml
benchmarks/benchmark_cartesian_dmp.py
benchmarks/benchmark_dmp.py
benchmarks/benchmark_dmp_phase.py
benchmarks/benchmark_dual_dmp.py
doc/Makefile
doc/make.bat
doc/source/api.rst
doc/source/conf.py
doc/source/index.md
doc/source/_static/241-logo-bmwi-jpg.jpg
doc/source/_static/DFKI_Logo.jpg
doc/source/_static/cart_dmp_ur5.png
doc/source/_static/conditional_promps.png
doc/source/_static/contextual_promps_kuka_panel_width_open3d.png
doc/source/_static/contextual_promps_kuka_panel_width_open3d2.png
doc/source/_static/coupled_dual_cart_dmps_gripper_open3d.png
doc/source/_static/coupled_dual_cart_dmps_rh5_pybullet.png
doc/source/_static/dmp_potential_field.png
doc/source/_static/dmp_state_space_distribution_kuka_peginhole_matplotlib.png
doc/source/_static/dmp_state_space_distribution_kuka_peginhole_open3d.png
doc/source/_static/dmp_ur5_minimum_jerk.gif
doc/source/_static/dmp_with_final_velocity.png
doc/source/_static/dual_cart_dmp_rh5_with_panel.gif
doc/source/_static/dual_cart_dmps_rh5_open3d.png
doc/source/_static/dual_cart_dmps_rh5_pybullet.png
doc/source/_static/promp_lasa.png
doc/source/_static/summary.png
doc/source/_static/summary.svg
doc/source/_templates/class.rst
docker/Dockerfile
examples/plot_cartesian_pose_coupling_dual_dmp.py
examples/plot_conditional_promp.py
examples/plot_coupling_1d_to_1d.py
examples/plot_coupling_3d_to_3d.py
examples/plot_critical_damping.py
examples/plot_dmp_1d_frequencies.py
examples/plot_dmp_2d_gain.py
examples/plot_dmp_potential_field.py
examples/plot_dmp_scaling.py
examples/plot_dmp_stepwise_execution.py
examples/plot_dmp_with_final_velocity.py
examples/plot_kinematics.py
examples/plot_minimum_jerk.py
examples/plot_obstacle_avoidance_2d.py
examples/plot_obstacle_avoidance_3d.py
examples/plot_promp_lasa.py
examples/plot_promp_multiple_viapoints.py
movement_primitives.egg-info/PKG-INFO
movement_primitives.egg-info/SOURCES.txt
movement_primitives.egg-info/dependency_links.txt
movement_primitives.egg-info/not-zip-safe
movement_primitives.egg-info/requires.txt
movement_primitives.egg-info/top_level.txt
