Metadata-Version: 2.1
Name: movement_primitives
Version: 0.9.1
Summary: Movement primitives
Home-page: https://github.com/dfki-ric/movement_primitives
Author: Alexander Fabisch
Author-email: alexander.fabisch@dfki.de
License: BSD-3-clause
Classifier: Programming Language :: Python :: 3
License-File: LICENSE
Provides-Extra: all
Requires-Dist: pytransform3d; extra == "all"
Requires-Dist: cython; extra == "all"
Requires-Dist: numpy; extra == "all"
Requires-Dist: scipy; extra == "all"
Requires-Dist: matplotlib; extra == "all"
Requires-Dist: open3d; extra == "all"
Requires-Dist: tqdm; extra == "all"
Requires-Dist: gmr; extra == "all"
Requires-Dist: PyYAML; extra == "all"
Requires-Dist: numba; extra == "all"
Requires-Dist: pybullet; extra == "all"
Provides-Extra: doc
Requires-Dist: sphinx; extra == "doc"
Requires-Dist: pydata-sphinx-theme; extra == "doc"
Requires-Dist: numpydoc; extra == "doc"
Requires-Dist: myst-parser; extra == "doc"
Provides-Extra: test
Requires-Dist: pytest; extra == "test"
Requires-Dist: pytest-cov; extra == "test"
